{"expireTime":9007200872721636000,"key":"transformer-remark-markdown-html-ast-46380aaa44b3246a346b07282de05249--","val":{"type":"root","children":[{"type":"element","tagName":"ul","properties":{},"children":[{"type":"text","value":"\n"},{"type":"element","tagName":"li","properties":{},"children":[{"type":"text","value":"Provided mentorship to students at all skill-levels in learning a broad array of languages from scratch to python to create new and classic games.","position":{"start":{"line":2,"column":3,"offset":3},"end":{"line":2,"column":149,"offset":149}}},{"type":"raw","value":"</p>","position":{"start":{"line":2,"column":149,"offset":149},"end":{"line":2,"column":153,"offset":153}}}],"position":{"start":{"line":2,"column":1,"offset":1},"end":{"line":3,"column":1,"offset":154}}},{"type":"text","value":"\n"},{"type":"element","tagName":"li","properties":{},"children":[{"type":"text","value":"Organized coder fairs, allowing students the opportunity to demonstrate their skills and introduce more advanced programmers to the world of Internet of Things (IoT).","position":{"start":{"line":4,"column":3,"offset":157},"end":{"line":4,"column":169,"offset":323}}},{"type":"raw","value":"</p>","position":{"start":{"line":4,"column":169,"offset":323},"end":{"line":4,"column":173,"offset":327}}}],"position":{"start":{"line":4,"column":1,"offset":155},"end":{"line":5,"column":1,"offset":328}}},{"type":"text","value":"\n"},{"type":"element","tagName":"li","properties":{},"children":[{"type":"text","value":"Wrote weekly notes and coder reviews providing parents with insight into their kids’ learning progress.","position":{"start":{"line":6,"column":3,"offset":331},"end":{"line":6,"column":106,"offset":434}}},{"type":"raw","value":"</p>","position":{"start":{"line":6,"column":106,"offset":434},"end":{"line":6,"column":110,"offset":438}}}],"position":{"start":{"line":6,"column":1,"offset":329},"end":{"line":6,"column":110,"offset":438}}},{"type":"text","value":"\n"}],"position":{"start":{"line":2,"column":1,"offset":1},"end":{"line":6,"column":110,"offset":438}}}],"position":{"start":{"line":1,"column":1,"offset":0},"end":{"line":7,"column":1,"offset":439}}}}